pretend.py
pretend-1.0.8.dist-info/DESCRIPTION.rst
pretend-1.0.8.dist-info/METADATA
pretend-1.0.8.dist-info/pydist.json
pretend-1.0.8.dist-info/RECORD
pretend-1.0.8.dist-info/top_level.txt
pretend-1.0.8.dist-info/WHEEL
